{
  "title": "Asana Case Studies Review: Driving Efficiency and Collaboration",
  "url": "https://asana.com/customers/ (summarized from third-party reviews)",
  "published_at": null,
  "updated_at": null,
  "author": null,
  "tags": ["asana", "case studies", "success stories", "efficiency", "productivity", "collaboration", "project management", "cost savings"],
  "content_type": "case_study",
  "word_count": 500,
  "content": "Asana is a work management platform designed to help organizations orchestrate their work, from small projects to strategic initiatives, by providing clarity, transparency, and accountability. Its case studies demonstrate a range of benefits for various businesses across different industries. Key benefits highlighted include significant cost savings, with companies like Morningstar saving an estimated $600,000 annually with AI-powered workflows, and Palo Alto Networks reducing operating costs by 40%. Increased efficiency and productivity are also common themes, with Asurion saving 37% in project initiation time and Zoom employees saving an estimated 335 days of work per year. Asana enhances team collaboration and communication by providing a unified space for real-time interaction, with 81% of customers reporting easier communication and 80% increased accountability. The platform offers robust tools for improved project management and task tracking, ensuring projects stay on track with clear deadlines and contributors. Asana's design supports scalability, allowing businesses to handle increasing tasks and projects efficiently. Case studies also emphasize clarity and goal alignment, with 68% of customers stating it makes their team's goals clearer. Specific examples include Accor's 100% efficiency improvements, Verizon's transformed campaign management, and KENDO's 87 workdays saved annually. Asana's platform is built on its 'Work Graph,' providing a foundation for human and AI collaboration, with continuous integration of AI capabilities to accelerate decision-making and improve productivity.",
  "links": [],
  "entities": ["Asana", "Morningstar", "Palo Alto Networks", "Zoom", "Accor", "Verizon", "Spotify", "KENDO", "Work Graph", "AI"],
  "language": "en"
}